config.yaml
kuiper/__init__.py
kuiper/db.py
kuiper/main.py
kuiper/models/Base.py
kuiper/models/Post.py
kuiper/models/User.py
kuiper/models/__init__.py
kuiper/remote/Client.py
kuiper/remote/Server.py
kuiper/remote/__init__.py
kuiper/tui/__init__.py
kuiper/tui/input.py
kuiper/tui/states.py
kuiper/tui/tui.py
kuiper/tui/utils.py
kuiper/tui/views.py
kuiper-0.8.15.dist-info/entry_points.txt
kuiper-0.8.15.dist-info/LICENSE
kuiper-0.8.15.dist-info/WHEEL
kuiper-0.8.15.dist-info/METADATA
kuiper-0.8.15.dist-info/RECORD
