Metadata-Version: 2.1
Name: kuiper
Version: 0.8.15
Summary: A terminal-based dating application for UTD students
Home-page: https://github.com/CharlesAverill/kuiper
License: GPL-3.0-only
Author: CharlesAverill
Author-email: charlesaverill20@gmail.com
Requires-Python: >=3.7,<4.0
Classifier: License :: OSI Approved :: GNU General Public License v3 (GPLv3)
Classifier: Programming Language :: Python :: 3
Classifier: Programming Language :: Python :: 3.7
Classifier: Programming Language :: Python :: 3.8
Classifier: Programming Language :: Python :: 3.9
Requires-Dist: PyYAML (==5.3)
Requires-Dist: email-validator (==1.1.3)
Requires-Dist: sqlalchemy (==1.4.20)
Requires-Dist: update-checker (==0.18.0)
Requires-Dist: websockets (==9.1)
Requires-Dist: werkzeug (==2.0.1)
